homework/four_adder/four_adder.v
module one_adder(output sum, output c_out,input c_in,input a,input b);
wire d,e,f;

xor g1(d,a,b);
xor g2(sum,d,c_in);
and g3(e,a,b);
and g4(f,d,c_in);
or  g5(c_out,e,f);

endmodule







module four_adder(output [3:0] sum,output c_out,input c_in,input [3:0] a,input [3:0] b);
wire    [2:0]   temp;

one_adder e(sum[0],temp[0],c_in,a[0],b[0]);
one_adder f(sum[1],temp[1],temp[0],a[1],b[1]);
one_adder g(sum[2],temp[2],temp[1],a[2],b[2]);
one_adder h(sum[3],c_out,temp[2],a[3],b[3]);


endmodule

homework/four_adder/four_adder_tb.vt
module main;
reg signed [3:0] a;
reg signed [3:0] b;
reg signed c;
wire signed [3:0] sum;
wire c_out;

four_adder test(sum, c_out, c, a, b);


initial
begin
    $dumpfile("test_four_adder.vcd");
    $dumpvars(0,main);
    a = 4'b0000;
    b = 4'b0000;
    c = 0;
    repeat(2)begin
	    repeat(16)begin
		    repeat(16)begin   
			$monitor("%dns monitor: a=%b b=%b c=%b sum=%b", $stime, a, b, c, sum);
			#2 b=b+1;
			end
		a=a+1;
        	b=0;
		end
    	a = 4'b0000;
    	b = 4'b0000;
    	c = 1;
	end
end
	



initial #2000 $finish;


endmodule

homework/four_adder/test_four_adder.vcd
$date
	Fri Dec 16 22:40:10 2022
$end
$version
	Icarus Verilog
$end
$timescale
	1s
$end
$scope module main $end
$var wire 4 ! sum [3:0] $end
$var wire 1 " c_out $end
$var reg 4 # a [3:0] $end
$var reg 4 $ b [3:0] $end
$var reg 1 % c $end
$scope module test $end
$var wire 4 & a [3:0] $end
$var wire 4 ' b [3:0] $end
$var wire 1 % c_in $end
$var wire 3 ( temp [2:0] $end
$var wire 4 ) sum [3:0] $end
$var wire 1 " c_out $end
$scope module e $end
$var wire 1 * a $end
$var wire 1 + b $end
$var wire 1 % c_in $end
$var wire 1 , c_out $end
$var wire 1 - d $end
$var wire 1 . e $end
$var wire 1 / f $end
$var wire 1 0 sum $end
$upscope $end
$scope module f $end
$var wire 1 1 a $end
$var wire 1 2 b $end
$var wire 1 3 c_in $end
$var wire 1 4 c_out $end
$var wire 1 5 d $end
$var wire 1 6 e $end
$var wire 1 7 f $end
$var wire 1 8 sum $end
$upscope $end
$scope module g $end
$var wire 1 9 a $end
$var wire 1 : b $end
$var wire 1 ; c_in $end
$var wire 1 < c_out $end
$var wire 1 = d $end
$var wire 1 > e $end
$var wire 1 ? f $end
$var wire 1 @ sum $end
$upscope $end
$scope module h $end
$var wire 1 A a $end
$var wire 1 B b $end
$var wire 1 C c_in $end
$var wire 1 " c_out $end
$var wire 1 D d $end
$var wire 1 E e $end
$var wire 1 F f $end
$var wire 1 G sum $end
$upscope $end
$upscope $end
$upscope $end
$enddefinitions $end
#0
$dumpvars
0G
0F
0E
0D
0C
0B
0A
0@
0?
0>
0=
0<
0;
0:
09
08
07
06
05
04
03
02
01
00
0/
0.
0-
0,
0+
0*
b0 )
b0 (
b0 '
b0 &
0%
b0 $
b0 #
0"
b0 !
$end
#2
b1 !
b1 )
10
1-
1+
b1 $
b1 '
#4
00
b10 !
b10 )
18
0-
15
0+
12
b10 $
b10 '
#6
b11 !
b11 )
10
1-
1+
b11 $
b11 '
#8
00
08
b100 !
b100 )
1@
0-
05
1=
0+
02
1:
b100 $
b100 '
#10
b101 !
b101 )
10
1-
1+
b101 $
b101 '
#12
00
b110 !
b110 )
18
0-
15
0+
12
b110 $
b110 '
#14
b111 !
b111 )
10
1-
1+
b111 $
b111 '
#16
00
08
0@
b1000 !
b1000 )
1G
0-
05
0=
1D
0+
02
0:
1B
b1000 $
b1000 '
#18
b1001 !
b1001 )
10
1-
1+
b1001 $
b1001 '
#20
00
b1010 !
b1010 )
18
0-
15
0+
12
b1010 $
b1010 '
#22
b1011 !
b1011 )
10
1-
1+
b1011 $
b1011 '
#24
00
08
b1100 !
b1100 )
1@
0-
05
1=
0+
02
1:
b1100 $
b1100 '
#26
b1101 !
b1101 )
10
1-
1+
b1101 $
b1101 '
#28
00
b1110 !
b1110 )
18
0-
15
0+
12
b1110 $
b1110 '
#30
b1111 !
b1111 )
10
1-
1+
b1111 $
b1111 '
#32
08
0@
b1 !
b1 )
0G
05
0=
0D
1*
0+
02
0:
0B
b1 #
b1 &
b0 $
b0 '
#34
18
13
b10 !
b10 )
00
b1 (
1,
0-
1.
1+
b1 $
b1 '
#36
0@
0;
03
04
10
b0 (
0,
b11 !
b11 )
18
07
1-
0.
15
0+
12
b10 $
b10 '
#38
1@
1;
14
08
17
13
b100 !
b100 )
00
b11 (
1,
0-
1.
1+
b11 $
b11 '
#40
0G
0;
0C
03
04
0<
10
b0 (
0,
08
07
b101 !
b101 )
1@
0?
1-
0.
05
1=
0+
02
1:
b100 $
b100 '
#42
18
13
b110 !
b110 )
00
b1 (
1,
0-
1.
1+
b101 $
b101 '
#44
0G
0C
0<
1@
0?
0;
03
04
10
b0 (
0,
b111 !
b111 )
18
07
1-
0.
15
0+
12
b110 $
b110 '
#46
1G
1C
1<
0@
1?
1;
14
08
17
13
b1000 !
b1000 )
00
b111 (
1,
0-
1.
1+
b111 $
b111 '
#48
0;
0C
03
04
0<
0"
10
b0 (
0,
08
07
0@
0?
b1001 !
b1001 )
1G
0F
1-
0.
05
0=
1D
0+
02
0:
1B
b1000 $
b1000 '
#50
18
13
b1010 !
b1010 )
00
b1 (
1,
0-
1.
1+
b1001 $
b1001 '
#52
0@
0;
03
04
10
b0 (
0,
b1011 !
b1011 )
18
07
1-
0.
15
0+
12
b1010 $
b1010 '
#54
1@
1;
14
08
17
13
b1100 !
b1100 )
00
b11 (
1,
0-
1.
1+
b1011 $
b1011 '
#56
0"
1G
0F
0;
0C
03
04
0<
10
b0 (
0,
08
07
b1101 !
b1101 )
1@
0?
1-
0.
05
1=
0+
02
1:
b1100 $
b1100 '
#58
18
13
b1110 !
b1110 )
00
b1 (
1,
0-
1.
1+
b1101 $
b1101 '
#60
0"
1G
0F
0C
0<
1@
0?
0;
03
04
10
b0 (
0,
b1111 !
b1111 )
18
07
1-
0.
15
0+
12
b1110 $
b1110 '
#62
1"
0G
1F
1C
1<
0@
1?
1;
14
08
17
13
b0 !
b0 )
00
b111 (
1,
0-
1.
1+
b1111 $
b1111 '
#64
0;
04
18
07
0C
03
0<
0"
b0 (
0,
0@
0?
b10 !
b10 )
0G
0F
0.
0=
0D
0*
11
0+
02
0:
0B
b10 #
b10 &
b0 $
b0 '
#66
b11 !
b11 )
10
1-
1+
b1 $
b1 '
#68
1@
1;
00
b100 !
b100 )
08
b10 (
14
0-
05
16
0+
12
b10 $
b10 '
#70
b101 !
b101 )
10
1-
1+
b11 $
b11 '
#72
0G
0C
0;
0<
00
18
b0 (
04
b110 !
b110 )
1@
0?
0-
15
06
1=
0+
02
1:
b100 $
b100 '
#74
b111 !
b111 )
10
1-
1+
b101 $
b101 '
#76
1G
1C
1<
0@
1?
1;
00
b1000 !
b1000 )
08
b110 (
14
0-
05
16
0+
12
b110 $
b110 '
#78
b1001 !
b1001 )
10
1-
1+
b111 $
b111 '
#80
0C
0;
0<
0"
00
18
b0 (
04
0@
0?
b1010 !
b1010 )
1G
0F
0-
15
06
0=
1D
0+
02
0:
1B
b1000 $
b1000 '
#82
b1011 !
b1011 )
10
1-
1+
b1001 $
b1001 '
#84
1@
1;
00
b1100 !
b1100 )
08
b10 (
14
0-
05
16
0+
12
b1010 $
b1010 '
#86
b1101 !
b1101 )
10
1-
1+
b1011 $
b1011 '
#88
0"
1G
0F
0C
0;
0<
00
18
b0 (
04
b1110 !
b1110 )
1@
0?
0-
15
06
1=
0+
02
1:
b1100 $
b1100 '
#90
b1111 !
b1111 )
10
1-
1+
b1101 $
b1101 '
#92
1"
0G
1F
1C
1<
0@
1?
1;
00
b0 !
b0 )
08
b110 (
14
0-
05
16
0+
12
b1110 $
b1110 '
#94
b1 !
b1 )
10
1-
1+
b1111 $
b1111 '
#96
0C
0;
0<
0"
18
b0 (
04
0@
0?
b11 !
b11 )
0G
0F
15
06
0=
0D
1*
0+
02
0:
0B
b11 #
b11 &
b0 $
b0 '
#98
1@
1;
14
08
17
13
b100 !
b100 )
00
b11 (
1,
0-
1.
1+
b1 $
b1 '
#100
03
10
b10 (
0,
b101 !
b101 )
08
07
1-
0.
05
16
0+
12
b10 $
b10 '
#102
18
13
b110 !
b110 )
00
b11 (
1,
0-
1.
1+
b11 $
b11 '
#104
0G
0C
03
0;
0<
10
0,
18
07
b0 (
04
b111 !
b111 )
1@
0?
1-
0.
15
06
1=
0+
02
1:
b100 $
b100 '
#106
1G
1C
1<
0@
1?
1;
14
08
17
13
b1000 !
b1000 )
00
b111 (
1,
0-
1.
1+
b101 $
b101 '
#108
03
10
b110 (
0,
b1001 !
b1001 )
08
07
1-
0.
05
16
0+
12
b110 $
b110 '
#110
18
13
b1010 !
b1010 )
00
b111 (
1,
0-
1.
1+
b111 $
b111 '
#112
0C
03
0;
0<
0"
10
0,
18
07
b0 (
04
0@
0?
b1011 !
b1011 )
1G
0F
1-
0.
15
06
0=
1D
0+
02
0:
1B
b1000 $
b1000 '
#114
1@
1;
14
08
17
13
b1100 !
b1100 )
00
b11 (
1,
0-
1.
1+
b1001 $
b1001 '
#116
03
10
b10 (
0,
b1101 !
b1101 )
08
07
1-
0.
05
16
0+
12
b1010 $
b1010 '
#118
18
13
b1110 !
b1110 )
00
b11 (
1,
0-
1.
1+
b1011 $
b1011 '
#120
0"
1G
0F
0C
03
0;
0<
10
0,
18
07
b0 (
04
b1111 !
b1111 )
1@
0?
1-
0.
15
06
1=
0+
02
1:
b1100 $
b1100 '
#122
1"
0G
1F
1C
1<
0@
1?
1;
14
08
17
13
b0 !
b0 )
00
b111 (
1,
0-
1.
1+
b1101 $
b1101 '
#124
03
10
b110 (
0,
b1 !
b1 )
08
07
1-
0.
05
16
0+
12
b1110 $
b1110 '
#126
18
13
b10 !
b10 )
00
b111 (
1,
0-
1.
1+
b1111 $
b1111 '
#128
0C
0<
08
1@
0?
03
0;
0"
0,
b0 (
04
b100 !
b100 )
0G
0F
0.
06
0D
0*
01
19
0+
02
0:
0B
b100 #
b100 &
b0 $
b0 '
#130
b101 !
b101 )
10
1-
1+
b1 $
b1 '
#132
00
b110 !
b110 )
18
0-
15
0+
12
b10 $
b10 '
#134
b111 !
b111 )
10
1-
1+
b11 $
b11 '
#136
1G
1C
00
08
b1000 !
b1000 )
0@
b100 (
1<
0-
05
0=
1>
0+
02
1:
b100 $
b100 '
#138
b1001 !
b1001 )
10
1-
1+
b101 $
b101 '
#140
00
b1010 !
b1010 )
18
0-
15
0+
12
b110 $
b110 '
#142
b1011 !
b1011 )
10
1-
1+
b111 $
b111 '
#144
0C
0"
00
08
1@
b0 (
0<
b1100 !
b1100 )
1G
0F
0-
05
1=
0>
1D
0+
02
0:
1B
b1000 $
b1000 '
#146
b1101 !
b1101 )
10
1-
1+
b1001 $
b1001 '
#148
00
b1110 !
b1110 )
18
0-
15
0+
12
b1010 $
b1010 '
#150
b1111 !
b1111 )
10
1-
1+
b1011 $
b1011 '
#152
1"
0G
1F
1C
00
08
b0 !
b0 )
0@
b100 (
1<
0-
05
0=
1>
0+
02
1:
b1100 $
b1100 '
#154
b1 !
b1 )
10
1-
1+
b1101 $
b1101 '
#156
00
b10 !
b10 )
18
0-
15
0+
12
b1110 $
b1110 '
#158
b11 !
b11 )
10
1-
1+
b1111 $
b1111 '
#160
0C
0"
08
1@
b0 (
0<
b101 !
b101 )
0G
0F
05
1=
0>
0D
1*
0+
02
0:
0B
b101 #
b101 &
b0 $
b0 '
#162
18
13
b110 !
b110 )
00
b1 (
1,
0-
1.
1+
b1 $
b1 '
#164
0G
0C
0<
1@
0?
0;
03
04
10
b0 (
0,
b111 !
b111 )
18
07
1-
0.
15
0+
12
b10 $
b10 '
#166
1G
1C
1<
0@
1?
1;
14
08
17
13
b1000 !
b1000 )
00
b111 (
1,
0-
1.
1+
b11 $
b11 '
#168
0;
03
04
10
b100 (
0,
08
07
b1001 !
b1001 )
0@
0?
1-
0.
05
0=
1>
0+
02
1:
b100 $
b100 '
#170
18
13
b1010 !
b1010 )
00
b101 (
1,
0-
1.
1+
b101 $
b101 '
#172
0@
0;
03
04
10
b100 (
0,
b1011 !
b1011 )
18
07
1-
0.
15
0+
12
b110 $
b110 '
#174
1@
1;
14
08
17
13
b1100 !
b1100 )
00
b111 (
1,
0-
1.
1+
b111 $
b111 '
#176
0;
03
04
0C
0"
10
0,
08
07
1@
0?
b0 (
0<
b1101 !
b1101 )
1G
0F
1-
0.
05
1=
0>
1D
0+
02
0:
1B
b1000 $
b1000 '
#178
18
13
b1110 !
b1110 )
00
b1 (
1,
0-
1.
1+
b1001 $
b1001 '
#180
0"
1G
0F
0C
0<
1@
0?
0;
03
04
10
b0 (
0,
b1111 !
b1111 )
18
07
1-
0.
15
0+
12
b1010 $
b1010 '
#182
1"
0G
1F
1C
1<
0@
1?
1;
14
08
17
13
b0 !
b0 )
00
b111 (
1,
0-
1.
1+
b1011 $
b1011 '
#184
0;
03
04
10
b100 (
0,
08
07
b1 !
b1 )
0@
0?
1-
0.
05
0=
1>
0+
02
1:
b1100 $
b1100 '
#186
18
13
b10 !
b10 )
00
b101 (
1,
0-
1.
1+
b1101 $
b1101 '
#188
0@
0;
03
04
10
b100 (
0,
b11 !
b11 )
18
07
1-
0.
15
0+
12
b1110 $
b1110 '
#190
1@
1;
14
08
17
13
b100 !
b100 )
00
b111 (
1,
0-
1.
1+
b1111 $
b1111 '
#192
0;
04
18
07
03
0C
0"
0,
1@
0?
b0 (
0<
b110 !
b110 )
0G
0F
0.
1=
0>
0D
0*
11
0+
02
0:
0B
b110 #
b110 &
b0 $
b0 '
#194
b111 !
b111 )
10
1-
1+
b1 $
b1 '
#196
1G
1C
1<
0@
1?
1;
00
b1000 !
b1000 )
08
b110 (
14
0-
05
16
0+
12
b10 $
b10 '
#198
b1001 !
b1001 )
10
1-
1+
b11 $
b11 '
#200
0;
00
18
b100 (
04
b1010 !
b1010 )
0@
0?
0-
15
06
0=
1>
0+
02
1:
b100 $
b100 '
#202
b1011 !
b1011 )
10
1-
1+
b101 $
b101 '
#204
1@
1;
00
b1100 !
b1100 )
08
b110 (
14
0-
05
16
0+
12
b110 $
b110 '
#206
b1101 !
b1101 )
10
1-
1+
b111 $
b111 '
#208
0;
0C
0"
00
18
04
1@
0?
b0 (
0<
b1110 !
b1110 )
1G
0F
0-
15
06
1=
0>
1D
0+
02
0:
1B
b1000 $
b1000 '
#210
b1111 !
b1111 )
10
1-
1+
b1001 $
b1001 '
#212
1"
0G
1F
1C
1<
0@
1?
1;
00
b0 !
b0 )
08
b110 (
14
0-
05
16
0+
12
b1010 $
b1010 '
#214
b1 !
b1 )
10
1-
1+
b1011 $
b1011 '
#216
0;
00
18
b100 (
04
b10 !
b10 )
0@
0?
0-
15
06
0=
1>
0+
02
1:
b1100 $
b1100 '
#218
b11 !
b11 )
10
1-
1+
b1101 $
b1101 '
#220
1@
1;
00
b100 !
b100 )
08
b110 (
14
0-
05
16
0+
12
b1110 $
b1110 '
#222
b101 !
b101 )
10
1-
1+
b1111 $
b1111 '
#224
0;
0C
0"
18
04
1@
0?
b0 (
0<
b111 !
b111 )
0G
0F
15
06
1=
0>
0D
1*
0+
02
0:
0B
b111 #
b111 &
b0 $
b0 '
#226
1G
1C
1<
0@
1?
1;
14
08
17
13
b1000 !
b1000 )
00
b111 (
1,
0-
1.
1+
b1 $
b1 '
#228
03
10
b110 (
0,
b1001 !
b1001 )
08
07
1-
0.
05
16
0+
12
b10 $
b10 '
#230
18
13
b1010 !
b1010 )
00
b111 (
1,
0-
1.
1+
b11 $
b11 '
#232
03
0;
10
0,
18
07
b100 (
04
b1011 !
b1011 )
0@
0?
1-
0.
15
06
0=
1>
0+
02
1:
b100 $
b100 '
#234
1@
1;
14
08
17
13
b1100 !
b1100 )
00
b111 (
1,
0-
1.
1+
b101 $
b101 '
#236
03
10
b110 (
0,
b1101 !
b1101 )
08
07
1-
0.
05
16
0+
12
b110 $
b110 '
#238
18
13
b1110 !
b1110 )
00
b111 (
1,
0-
1.
1+
b111 $
b111 '
#240
03
0;
0C
0"
10
0,
18
07
04
1@
0?
b0 (
0<
b1111 !
b1111 )
1G
0F
1-
0.
15
06
1=
0>
1D
0+
02
0:
1B
b1000 $
b1000 '
#242
1"
0G
1F
1C
1<
0@
1?
1;
14
08
17
13
b0 !
b0 )
00
b111 (
1,
0-
1.
1+
b1001 $
b1001 '
#244
03
10
b110 (
0,
b1 !
b1 )
08
07
1-
0.
05
16
0+
12
b1010 $
b1010 '
#246
18
13
b10 !
b10 )
00
b111 (
1,
0-
1.
1+
b1011 $
b1011 '
#248
03
0;
10
0,
18
07
b100 (
04
b11 !
b11 )
0@
0?
1-
0.
15
06
0=
1>
0+
02
1:
b1100 $
b1100 '
#250
1@
1;
14
08
17
13
b100 !
b100 )
00
b111 (
1,
0-
1.
1+
b1101 $
b1101 '
#252
03
10
b110 (
0,
b101 !
b101 )
08
07
1-
0.
05
16
0+
12
b1110 $
b1110 '
#254
18
13
b110 !
b110 )
00
b111 (
1,
0-
1.
1+
b1111 $
b1111 '
#256
0"
08
0@
b1000 !
b1000 )
1G
0F
03
0;
0C
0,
04
b0 (
0<
0.
06
0>
0*
01
09
1A
0+
02
0:
0B
b1000 #
b1000 &
b0 $
b0 '
#258
b1001 !
b1001 )
10
1-
1+
b1 $
b1 '
#260
00
b1010 !
b1010 )
18
0-
15
0+
12
b10 $
b10 '
#262
b1011 !
b1011 )
10
1-
1+
b11 $
b11 '
#264
00
08
b1100 !
b1100 )
1@
0-
05
1=
0+
02
1:
b100 $
b100 '
#266
b1101 !
b1101 )
10
1-
1+
b101 $
b101 '
#268
00
b1110 !
b1110 )
18
0-
15
0+
12
b110 $
b110 '
#270
b1111 !
b1111 )
10
1-
1+
b111 $
b111 '
#272
00
08
0@
b0 !
b0 )
0G
1"
0-
05
0=
0D
1E
0+
02
0:
1B
b1000 $
b1000 '
#274
b1 !
b1 )
10
1-
1+
b1001 $
b1001 '
#276
00
b10 !
b10 )
18
0-
15
0+
12
b1010 $
b1010 '
#278
b11 !
b11 )
10
1-
1+
b1011 $
b1011 '
#280
00
08
b100 !
b100 )
1@
0-
05
1=
0+
02
1:
b1100 $
b1100 '
#282
b101 !
b101 )
10
1-
1+
b1101 $
b1101 '
#284
00
b110 !
b110 )
18
0-
15
0+
12
b1110 $
b1110 '
#286
b111 !
b111 )
10
1-
1+
b1111 $
b1111 '
#288
08
0@
b1001 !
b1001 )
1G
0"
05
0=
1D
0E
1*
0+
02
0:
0B
b1001 #
b1001 &
b0 $
b0 '
#290
18
13
b1010 !
b1010 )
00
b1 (
1,
0-
1.
1+
b1 $
b1 '
#292
0@
0;
03
04
10
b0 (
0,
b1011 !
b1011 )
18
07
1-
0.
15
0+
12
b10 $
b10 '
#294
1@
1;
14
08
17
13
b1100 !
b1100 )
00
b11 (
1,
0-
1.
1+
b11 $
b11 '
#296
0"
1G
0F
0;
0C
03
04
0<
10
b0 (
0,
08
07
b1101 !
b1101 )
1@
0?
1-
0.
05
1=
0+
02
1:
b100 $
b100 '
#298
18
13
b1110 !
b1110 )
00
b1 (
1,
0-
1.
1+
b101 $
b101 '
#300
0"
1G
0F
0C
0<
1@
0?
0;
03
04
10
b0 (
0,
b1111 !
b1111 )
18
07
1-
0.
15
0+
12
b110 $
b110 '
#302
1"
0G
1F
1C
1<
0@
1?
1;
14
08
17
13
b0 !
b0 )
00
b111 (
1,
0-
1.
1+
b111 $
b111 '
#304
0;
0C
03
04
0<
10
b0 (
0,
08
07
0@
0?
b1 !
b1 )
0G
0F
1-
0.
05
0=
0D
1E
0+
02
0:
1B
b1000 $
b1000 '
#306
18
13
b10 !
b10 )
00
b1 (
1,
0-
1.
1+
b1001 $
b1001 '
#308
0@
0;
03
04
10
b0 (
0,
b11 !
b11 )
18
07
1-
0.
15
0+
12
b1010 $
b1010 '
#310
1@
1;
14
08
17
13
b100 !
b100 )
00
b11 (
1,
0-
1.
1+
b1011 $
b1011 '
#312
0G
0;
0C
03
04
0<
10
b0 (
0,
08
07
b101 !
b101 )
1@
0?
1-
0.
05
1=
0+
02
1:
b1100 $
b1100 '
#314
18
13
b110 !
b110 )
00
b1 (
1,
0-
1.
1+
b1101 $
b1101 '
#316
0G
0C
0<
1@
0?
0;
03
04
10
b0 (
0,
b111 !
b111 )
18
07
1-
0.
15
0+
12
b1110 $
b1110 '
#318
1G
1C
1<
0@
1?
1;
14
08
17
13
b1000 !
b1000 )
00
b111 (
1,
0-
1.
1+
b1111 $
b1111 '
#320
0;
04
18
07
0C
03
0<
b0 (
0,
0@
0?
b1010 !
b1010 )
1G
0F
0"
0.
0=
1D
0E
0*
11
0+
02
0:
0B
b1010 #
b1010 &
b0 $
b0 '
#322
b1011 !
b1011 )
10
1-
1+
b1 $
b1 '
#324
1@
1;
00
b1100 !
b1100 )
08
b10 (
14
0-
05
16
0+
12
b10 $
b10 '
#326
b1101 !
b1101 )
10
1-
1+
b11 $
b11 '
#328
0"
1G
0F
0C
0;
0<
00
18
b0 (
04
b1110 !
b1110 )
1@
0?
0-
15
06
1=
0+
02
1:
b100 $
b100 '
#330
b1111 !
b1111 )
10
1-
1+
b101 $
b101 '
#332
1"
0G
1F
1C
1<
0@
1?
1;
00
b0 !
b0 )
08
b110 (
14
0-
05
16
0+
12
b110 $
b110 '
#334
b1 !
b1 )
10
1-
1+
b111 $
b111 '
#336
0C
0;
0<
00
18
b0 (
04
0@
0?
b10 !
b10 )
0G
0F
0-
15
06
0=
0D
1E
0+
02
0:
1B
b1000 $
b1000 '
#338
b11 !
b11 )
10
1-
1+
b1001 $
b1001 '
#340
1@
1;
00
b100 !
b100 )
08
b10 (
14
0-
05
16
0+
12
b1010 $
b1010 '
#342
b101 !
b101 )
10
1-
1+
b1011 $
b1011 '
#344
0G
0C
0;
0<
00
18
b0 (
04
b110 !
b110 )
1@
0?
0-
15
06
1=
0+
02
1:
b1100 $
b1100 '
#346
b111 !
b111 )
10
1-
1+
b1101 $
b1101 '
#348
1G
1C
1<
0@
1?
1;
00
b1000 !
b1000 )
08
b110 (
14
0-
05
16
0+
12
b1110 $
b1110 '
#350
b1001 !
b1001 )
10
1-
1+
b1111 $
b1111 '
#352
0C
0;
0<
18
b0 (
04
0@
0?
b1011 !
b1011 )
1G
0F
0"
15
06
0=
1D
0E
1*
0+
02
0:
0B
b1011 #
b1011 &
b0 $
b0 '
#354
1@
1;
14
08
17
13
b1100 !
b1100 )
00
b11 (
1,
0-
1.
1+
b1 $
b1 '
#356
03
10
b10 (
0,
b1101 !
b1101 )
08
07
1-
0.
05
16
0+
12
b10 $
b10 '
#358
18
13
b1110 !
b1110 )
00
b11 (
1,
0-
1.
1+
b11 $
b11 '
#360
0"
1G
0F
0C
03
0;
0<
10
0,
18
07
b0 (
04
b1111 !
b1111 )
1@
0?
1-
0.
15
06
1=
0+
02
1:
b100 $
b100 '
#362
1"
0G
1F
1C
1<
0@
1?
1;
14
08
17
13
b0 !
b0 )
00
b111 (
1,
0-
1.
1+
b101 $
b101 '
#364
03
10
b110 (
0,
b1 !
b1 )
08
07
1-
0.
05
16
0+
12
b110 $
b110 '
#366
18
13
b10 !
b10 )
00
b111 (
1,
0-
1.
1+
b111 $
b111 '
#368
0C
03
0;
0<
10
0,
18
07
b0 (
04
0@
0?
b11 !
b11 )
0G
0F
1-
0.
15
06
0=
0D
1E
0+
02
0:
1B
b1000 $
b1000 '
#370
1@
1;
14
08
17
13
b100 !
b100 )
00
b11 (
1,
0-
1.
1+
b1001 $
b1001 '
#372
03
10
b10 (
0,
b101 !
b101 )
08
07
1-
0.
05
16
0+
12
b1010 $
b1010 '
#374
18
13
b110 !
b110 )
00
b11 (
1,
0-
1.
1+
b1011 $
b1011 '
#376
0G
0C
03
0;
0<
10
0,
18
07
b0 (
04
b111 !
b111 )
1@
0?
1-
0.
15
06
1=
0+
02
1:
b1100 $
b1100 '
#378
1G
1C
1<
0@
1?
1;
14
08
17
13
b1000 !
b1000 )
00
b111 (
1,
0-
1.
1+
b1101 $
b1101 '
#380
03
10
b110 (
0,
b1001 !
b1001 )
08
07
1-
0.
05
16
0+
12
b1110 $
b1110 '
#382
18
13
b1010 !
b1010 )
00
b111 (
1,
0-
1.
1+
b1111 $
b1111 '
#384
0C
0<
08
1@
0?
03
0;
0,
b0 (
04
b1100 !
b1100 )
1G
0F
0"
0.
06
1D
0E
0*
01
19
0+
02
0:
0B
b1100 #
b1100 &
b0 $
b0 '
#386
b1101 !
b1101 )
10
1-
1+
b1 $
b1 '
#388
00
b1110 !
b1110 )
18
0-
15
0+
12
b10 $
b10 '
#390
b1111 !
b1111 )
10
1-
1+
b11 $
b11 '
#392
1"
0G
1F
1C
00
08
b0 !
b0 )
0@
b100 (
1<
0-
05
0=
1>
0+
02
1:
b100 $
b100 '
#394
b1 !
b1 )
10
1-
1+
b101 $
b101 '
#396
00
b10 !
b10 )
18
0-
15
0+
12
b110 $
b110 '
#398
b11 !
b11 )
10
1-
1+
b111 $
b111 '
#400
0C
00
08
1@
b0 (
0<
b100 !
b100 )
0G
0F
0-
05
1=
0>
0D
1E
0+
02
0:
1B
b1000 $
b1000 '
#402
b101 !
b101 )
10
1-
1+
b1001 $
b1001 '
#404
00
b110 !
b110 )
18
0-
15
0+
12
b1010 $
b1010 '
#406
b111 !
b111 )
10
1-
1+
b1011 $
b1011 '
#408
1G
1C
00
08
b1000 !
b1000 )
0@
b100 (
1<
0-
05
0=
1>
0+
02
1:
b1100 $
b1100 '
#410
b1001 !
b1001 )
10
1-
1+
b1101 $
b1101 '
#412
00
b1010 !
b1010 )
18
0-
15
0+
12
b1110 $
b1110 '
#414
b1011 !
b1011 )
10
1-
1+
b1111 $
b1111 '
#416
0C
08
1@
b0 (
0<
b1101 !
b1101 )
1G
0F
0"
05
1=
0>
1D
0E
1*
0+
02
0:
0B
b1101 #
b1101 &
b0 $
b0 '
#418
18
13
b1110 !
b1110 )
00
b1 (
1,
0-
1.
1+
b1 $
b1 '
#420
0"
1G
0F
0C
0<
1@
0?
0;
03
04
10
b0 (
0,
b1111 !
b1111 )
18
07
1-
0.
15
0+
12
b10 $
b10 '
#422
1"
0G
1F
1C
1<
0@
1?
1;
14
08
17
13
b0 !
b0 )
00
b111 (
1,
0-
1.
1+
b11 $
b11 '
#424
0;
03
04
10
b100 (
0,
08
07
b1 !
b1 )
0@
0?
1-
0.
05
0=
1>
0+
02
1:
b100 $
b100 '
#426
18
13
b10 !
b10 )
00
b101 (
1,
0-
1.
1+
b101 $
b101 '
#428
0@
0;
03
04
10
b100 (
0,
b11 !
b11 )
18
07
1-
0.
15
0+
12
b110 $
b110 '
#430
1@
1;
14
08
17
13
b100 !
b100 )
00
b111 (
1,
0-
1.
1+
b111 $
b111 '
#432
0;
03
04
0C
10
0,
08
07
1@
0?
b0 (
0<
b101 !
b101 )
0G
0F
1-
0.
05
1=
0>
0D
1E
0+
02
0:
1B
b1000 $
b1000 '
#434
18
13
b110 !
b110 )
00
b1 (
1,
0-
1.
1+
b1001 $
b1001 '
#436
0G
0C
0<
1@
0?
0;
03
04
10
b0 (
0,
b111 !
b111 )
18
07
1-
0.
15
0+
12
b1010 $
b1010 '
#438
1G
1C
1<
0@
1?
1;
14
08
17
13
b1000 !
b1000 )
00
b111 (
1,
0-
1.
1+
b1011 $
b1011 '
#440
0;
03
04
10
b100 (
0,
08
07
b1001 !
b1001 )
0@
0?
1-
0.
05
0=
1>
0+
02
1:
b1100 $
b1100 '
#442
18
13
b1010 !
b1010 )
00
b101 (
1,
0-
1.
1+
b1101 $
b1101 '
#444
0@
0;
03
04
10
b100 (
0,
b1011 !
b1011 )
18
07
1-
0.
15
0+
12
b1110 $
b1110 '
#446
1@
1;
14
08
17
13
b1100 !
b1100 )
00
b111 (
1,
0-
1.
1+
b1111 $
b1111 '
#448
0;
04
18
07
03
0C
0,
1@
0?
b0 (
0<
b1110 !
b1110 )
1G
0F
0"
0.
1=
0>
1D
0E
0*
11
0+
02
0:
0B
b1110 #
b1110 &
b0 $
b0 '
#450
b1111 !
b1111 )
10
1-
1+
b1 $
b1 '
#452
1"
0G
1F
1C
1<
0@
1?
1;
00
b0 !
b0 )
08
b110 (
14
0-
05
16
0+
12
b10 $
b10 '
#454
b1 !
b1 )
10
1-
1+
b11 $
b11 '
#456
0;
00
18
b100 (
04
b10 !
b10 )
0@
0?
0-
15
06
0=
1>
0+
02
1:
b100 $
b100 '
#458
b11 !
b11 )
10
1-
1+
b101 $
b101 '
#460
1@
1;
00
b100 !
b100 )
08
b110 (
14
0-
05
16
0+
12
b110 $
b110 '
#462
b101 !
b101 )
10
1-
1+
b111 $
b111 '
#464
0;
0C
00
18
04
1@
0?
b0 (
0<
b110 !
b110 )
0G
0F
0-
15
06
1=
0>
0D
1E
0+
02
0:
1B
b1000 $
b1000 '
#466
b111 !
b111 )
10
1-
1+
b1001 $
b1001 '
#468
1G
1C
1<
0@
1?
1;
00
b1000 !
b1000 )
08
b110 (
14
0-
05
16
0+
12
b1010 $
b1010 '
#470
b1001 !
b1001 )
10
1-
1+
b1011 $
b1011 '
#472
0;
00
18
b100 (
04
b1010 !
b1010 )
0@
0?
0-
15
06
0=
1>
0+
02
1:
b1100 $
b1100 '
#474
b1011 !
b1011 )
10
1-
1+
b1101 $
b1101 '
#476
1@
1;
00
b1100 !
b1100 )
08
b110 (
14
0-
05
16
0+
12
b1110 $
b1110 '
#478
b1101 !
b1101 )
10
1-
1+
b1111 $
b1111 '
