one_adder/one_adder.v
module one_adder(sum,c_out,c_in,a,b);
input c_in,a,b;
output sum,c_out;
wire d,e,f;


xor a_xor_b(d,a,b),
    a_xor_b_xor_c(sum,d,c_in);
and a_and_b(e,a,b),
    a_xor_b_and_c(f,d,c_in);
or  out(c_out,e,f);

endmodule

one_adder/one_adder_tb.v
module one_adder_tb;

reg a,b,c_in;
wire s,c_out;

one_adder test(s,c_out,c_in,a,b);


initial begin
    $dumpfile("test_one_adder.vcd");
    $dumpvars(0,one_adder_tb);
    #2 c_in=1'b0;  a=1'b0;  b=1'b0;
    #2 c_in=1'b0;  a=1'b1;  b=1'b0;
    #2 c_in=1'b0;  a=1'b0;  b=1'b1;
    #2 c_in=1'b0;  a=1'b1;  b=1'b1;
    #2 c_in=1'b1;  a=1'b0;  b=1'b0;
    #2 c_in=1'b1;  a=1'b1;  b=1'b0;
    #2 c_in=1'b1;  a=1'b0;  b=1'b1;
    #2 c_in=1'b1;  a=1'b1;  b=1'b1;

    #20 $finish;

end
    

endmodule

one_adder/one_adder.vcd
$date
	Mon Dec 12 23:10:39 2022
$end
$version
	Icarus Verilog
$end
$timescale
	1s
$end
$scope module one_adder_tb $end
$var wire 1 ! s $end
$var wire 1 " c_out $end
$var reg 1 # a $end
$var reg 1 $ b $end
$var reg 1 % c_in $end
$scope module test $end
$var wire 1 # a $end
$var wire 1 $ b $end
$var wire 1 % c_in $end
$var wire 1 " c_out $end
$var wire 1 & d $end
$var wire 1 ' e $end
$var wire 1 ( f $end
$var wire 1 ! sum $end
$upscope $end
$upscope $end
$enddefinitions $end
#0
$dumpvars
x(
x'
x&
x%
x$
x#
x"
x!
$end
#2
0!
0"
0&
0'
0(
0$
0#
0%
#4
1!
1&
1#
#6
1$
0#
#8
0!
1"
0&
1'
1#
#10
0"
0'
1!
0$
0#
1%
#12
1"
0!
1(
1&
1#
#14
1$
0#
#16
1!
0(
0&
1'
1#
